pyxdameraulevenshtein/__init__.py
pyxdameraulevenshtein/__init__.pyi
pyxdameraulevenshtein/_initialize.cp314-win_amd64.pyd
pyxdameraulevenshtein/_initialize.pyx
pyxdameraulevenshtein/py.typed
pyxdameraulevenshtein-1.9.0.dist-info/licenses/AUTHORS.md
pyxdameraulevenshtein-1.9.0.dist-info/licenses/LICENSE
pyxdameraulevenshtein-1.9.0.dist-info/METADATA
pyxdameraulevenshtein-1.9.0.dist-info/WHEEL
pyxdameraulevenshtein-1.9.0.dist-info/top_level.txt
pyxdameraulevenshtein-1.9.0.dist-info/RECORD
