Metadata-Version: 2.1
Name: pyxDamerauLevenshtein
Version: 1.9.0
Summary: pyxDamerauLevenshtein implements the Damerau-Levenshtein (DL) edit distance algorithm for Python in Cython for high performance.
Home-page: https://github.com/lanl/pyxDamerauLevenshtein
Author: Geoffrey Fairchild
Author-email: mail@gfairchild.com
Maintainer: Geoffrey Fairchild
Maintainer-email: mail@gfairchild.com
License: BSD 3-Clause License
Classifier: Development Status :: 5 - Production/Stable
Classifier: Intended Audience :: Developers
Classifier: Intended Audience :: Education
Classifier: Intended Audience :: Science/Research
Classifier: License :: OSI Approved :: BSD License
Classifier: Operating System :: OS Independent
Classifier: Programming Language :: Cython
Classifier: Programming Language :: Python :: 3
Classifier: Programming Language :: Python :: 3.9
Classifier: Programming Language :: Python :: 3.10
Classifier: Programming Language :: Python :: 3.11
Classifier: Programming Language :: Python :: 3.12
Classifier: Programming Language :: Python :: 3.13
Classifier: Programming Language :: Python :: 3.14
Classifier: Topic :: Scientific/Engineering :: Bio-Informatics
Classifier: Topic :: Scientific/Engineering :: Information Analysis
Classifier: Topic :: Text Processing :: Linguistic
License-File: LICENSE
License-File: AUTHORS.md
